yml2db/__init__.py
yml2db/db_config.ini.sample
yml2db/db_from_schema_yaml.py
yml2db/yml2db_main.py
yml2db-0.3.dist-info/DESCRIPTION.rst
yml2db-0.3.dist-info/METADATA
yml2db-0.3.dist-info/RECORD
yml2db-0.3.dist-info/WHEEL
yml2db-0.3.dist-info/entry_points.txt
yml2db-0.3.dist-info/metadata.json
yml2db-0.3.dist-info/top_level.txt
