Metadata-Version: 2.0
Name: yml2db
Version: 0.3
Summary: Update database by changing schema yaml file
Home-page: https://github.com/wensheng/yml2db
Author: Wensheng Wang
Author-email: wenshengwang@gmail.com
License: MIT
Keywords: database schema mysql postgresql yaml
Platform: UNKNOWN
Classifier: Development Status :: 4 - Beta
Classifier: Intended Audience :: Developers
Classifier: Topic :: Software Development
Classifier: Topic :: Database
Classifier: License :: OSI Approved :: MIT License
Classifier: Programming Language :: Python :: 2
Classifier: Programming Language :: Python :: 3
Requires-Dist: pyyaml
Requires-Dist: pymysql
